<?xml version="1.0"?>

<!DOCTYPE suppressions PUBLIC
        "-//Checkstyle//DTD SuppressionFilter Configuration 1.2//EN"
        "https://checkstyle.org/dtds/suppressions_1_2.dtd">

<suppressions>
    <suppress checks="AtclauseOrder" files="."/>
    <suppress checks="AvoidEscapedUnicodeCharacters" files="."/>
    <suppress checks="AvoidStarImport" files="."/>
    <suppress checks="CustomImportOrder" files="."/>
    <suppress checks="JavadocMethod" files="."/>
    <suppress checks="JavadocParagraph" files="."/>
    <suppress checks="JavadocType" files="."/>
    <suppress checks="NonEmptyAtclauseDescription" files="."/>
    <suppress checks="SummaryJavadoc" files="."/>
    <suppress checks="UnusedImport" files="."/>
</suppressions>
